dahitiapi/API.py
dahitiapi/DAHITI.py
dahitiapi/Exceptions.py
dahitiapi/InSitu.py
dahitiapi/PLD.py
dahitiapi/SWORD.py
dahitiapi/__init__.py
dahitiapi/_version.py
dahitiapi-0.0.27.dist-info/METADATA
dahitiapi-0.0.27.dist-info/WHEEL
dahitiapi-0.0.27.dist-info/top_level.txt
dahitiapi-0.0.27.dist-info/RECORD
