Metadata-Version: 2.4
Name: dahitiapi
Version: 0.0.27
Summary: DAHITI-API
Author: Christian Schwatke
Author-email: christian.schwatke@tum.de
License: MIT
Project-URL: DAHITI Homepage, https://dahiti.dgfi.tum.de/
Project-URL: Documentation, https://dahiti-api.readthedocs.io/
Project-URL: Source Code, https://gitlab.lrz.de/openadb/python3-dahitiapi/
Classifier: Programming Language :: Python :: 3
Classifier: Operating System :: OS Independent
Requires-Python: >=3.8
Dynamic: author
Dynamic: author-email
Dynamic: classifier
Dynamic: description
Dynamic: description-content-type
Dynamic: license
Dynamic: project-url
Dynamic: requires-python
Dynamic: summary
